gsheet_tools-0.2.0.dist-info/METADATA
gsheet_tools-0.2.0.dist-info/WHEEL
gsheet_tools-0.2.0.dist-info/entry_points.txt
gsheet_tools-0.2.0.dist-info/licenses/LICENSE
gsheet_tools/__init__.py
gsheet_tools/_exceptions.py
gsheet_tools/_tools.py
gsheet_tools/flows.py
gsheet_tools-0.2.0.dist-info/RECORD
