Metadata-Version: 2.1
Name: gsheet_tools
Version: 0.2.0
Summary: Assistive development tool for implementing google sheet related operations and scenarios in python projects
Author-Email: Ankit Yadav <ankit8290@gmail.com>
License: MIT
Requires-Python: >=3.10
Requires-Dist: pandas>=2.3.3
